pumas/__init__.py
pumas/py.typed
pumas/aggregation/__init__.py
pumas/aggregation/aggregation.py
pumas/aggregation/aggregation_utils.py
pumas/aggregation/base_models.py
pumas/aggregation/catalogue.py
pumas/aggregation/exceptions.py
pumas/aggregation/weighted_arithmetic_mean.py
pumas/aggregation/weighted_deviation_index.py
pumas/aggregation/weighted_geometric_mean.py
pumas/aggregation/weighted_harmonic_mean.py
pumas/aggregation/weighted_product.py
pumas/aggregation/weighted_summation.py
pumas/architecture/__init__.py
pumas/architecture/catalogue.py
pumas/architecture/exceptions.py
pumas/architecture/parameters.py
pumas/architecture/parametrized_strategy.py
pumas/dataframes/__init__.py
pumas/dataframes/dataframe.py
pumas/dataframes/dataframe_utils.py
pumas/dataframes/exceptions.py
pumas/desirability/__init__.py
pumas/desirability/base_models.py
pumas/desirability/bell.py
pumas/desirability/catalogue.py
pumas/desirability/desirability.py
pumas/desirability/desirability_utility_functions.py
pumas/desirability/double_sigmoid.py
pumas/desirability/exponential_decay.py
pumas/desirability/multistep.py
pumas/desirability/sigmoid.py
pumas/desirability/sigmoid_bell.py
pumas/desirability/step.py
pumas/desirability/value_mapping.py
pumas/interfaces/__init__.py
pumas/parallelization/parallel_utils.py
pumas/plotting/__init__.py
pumas/plotting/desirability_parameter_analysis.py
pumas/plotting/plotter.py
pumas/reporting/exceptions.py
pumas/scoring_framework/__init__.py
pumas/scoring_framework/base_models.py
pumas/scoring_framework/example_usage.py
pumas/scoring_framework/factory.py
pumas/scoring_framework/models.py
pumas/scoring_framework/numeric_foerp.py
pumas/scoring_framework/numeric_noerp.py
pumas/scoring_framework/scoring_function.py
pumas/scoring_framework/type_definitions.py
pumas/scoring_profile/__init__.py
pumas/scoring_profile/models.py
pumas/uncertainty_management/__init__.py
pumas/uncertainty_management/distributions/models.py
pumas-1.3.0.dist-info/licenses/LICENSE
pumas-1.3.0.dist-info/METADATA
pumas-1.3.0.dist-info/WHEEL
pumas-1.3.0.dist-info/top_level.txt
pumas-1.3.0.dist-info/RECORD
