Metadata-Version: 2.4
Name: pumas
Version: 1.3.0
Summary: PUMAS is a Python package implementing a multi-objective scoring systems based on desirability functions and aggregation.
Project-URL: homepage, https://github.com/syngenta/pumas
Project-URL: repository, https://github.com/syngenta/pumas
Classifier: Intended Audience :: Science/Research
Classifier: Operating System :: MacOS :: MacOS X
Classifier: Operating System :: Microsoft :: Windows
Classifier: Operating System :: OS Independent
Classifier: Operating System :: POSIX :: Linux
Classifier: Programming Language :: Python
Classifier: Programming Language :: Python :: 3
Classifier: Programming Language :: Python :: 3 :: Only
Classifier: Programming Language :: Python :: 3.9
Classifier: Programming Language :: Python :: 3.10
Classifier: Programming Language :: Python :: 3.11
Classifier: Topic :: Scientific/Engineering
Requires-Python: >=3.9
License-File: LICENSE
Requires-Dist: pydantic>=2.10.0
Requires-Dist: numpy
Provides-Extra: dev
Requires-Dist: bumpver; extra == "dev"
Requires-Dist: pytest; extra == "dev"
Requires-Dist: pytest-cov; extra == "dev"
Requires-Dist: pytest-mock; extra == "dev"
Requires-Dist: sphinx; extra == "dev"
Requires-Dist: sphinx_toolbox; extra == "dev"
Requires-Dist: sphinxcontrib-napoleon; extra == "dev"
Requires-Dist: sphinxcontrib.mermaid; extra == "dev"
Requires-Dist: matplotlib; extra == "dev"
Requires-Dist: black; extra == "dev"
Requires-Dist: flake8; extra == "dev"
Requires-Dist: isort; extra == "dev"
Requires-Dist: pre-commit; extra == "dev"
Requires-Dist: jupyter; extra == "dev"
Requires-Dist: black[jupyter]; extra == "dev"
Requires-Dist: uncertainties; extra == "dev"
Requires-Dist: scipy; extra == "dev"
Provides-Extra: uncertainty
Requires-Dist: uncertainties; extra == "uncertainty"
Requires-Dist: scipy; extra == "uncertainty"
Provides-Extra: graphics
Requires-Dist: matplotlib; extra == "graphics"
Dynamic: license-file
